pysudoers/__init__.py
pysudoers-3.0.0.dist-info/LICENSE.txt
pysudoers-3.0.0.dist-info/METADATA
pysudoers-3.0.0.dist-info/WHEEL
pysudoers-3.0.0.dist-info/RECORD
