Metadata-Version: 2.3
Name: pysudoers
Version: 3.0.0
Summary: Python interface to the Linux sudoers file
License: BSD-3-Clause
Keywords: linux,sudoers
Author: Andrew Teixeira
Author-email: <teixeira@broadinstitute.org>
Requires-Python: >=3.9,<4.0.0
Classifier: License :: OSI Approved :: BSD License
Classifier: Programming Language :: Python :: 3
Classifier: Programming Language :: Python :: 3.9
Classifier: Programming Language :: Python :: 3.10
Classifier: Programming Language :: Python :: 3.11
Classifier: Programming Language :: Python :: 3.12
Classifier: Programming Language :: Python :: 3.13
Requires-Dist: toml (>=0.10.2,<0.11.0)
Project-URL: Homepage, https://github.com/broadinstitute/python-sudoers.git
Project-URL: Repository, https://github.com/broadinstitute/python-sudoers.git
